hidtools/__init__.py
hidtools/_version.py
hidtools/hid.py
hidtools/hidraw.py
hidtools/hut.py
hidtools/py.typed
hidtools/uhid.py
hidtools/util.py
hidtools/cli/decode.py
hidtools/cli/feature.py
hidtools/cli/parse_hid.py
hidtools/cli/record.py
hidtools/cli/replay.py
hidtools/data/0000_undefined.hut
hidtools/data/0001_generic_desktop.hut
hidtools/data/0002_simulation_controls.hut
hidtools/data/0003_vr_controls.hut
hidtools/data/0004_sports_controls.hut
hidtools/data/0005_gaming_controls.hut
hidtools/data/0006_generic_device_controls.hut
hidtools/data/0007_keyboard.hut
hidtools/data/0008_leds.hut
hidtools/data/0009_button.hut
hidtools/data/000a_ordinals.hut
hidtools/data/000b_telephony_devices.hut
hidtools/data/000c_consumer_devices.hut
hidtools/data/000d_digitizers.hut
hidtools/data/000e_haptic_page.hut
hidtools/data/0010_unicode.hut
hidtools/data/0012_eye_and_head_trackers.hut
hidtools/data/0014_auxiliary_display.hut
hidtools/data/0020_sensor.hut
hidtools/data/0040_medical_instruments.hut
hidtools/data/0041_braille_display.hut
hidtools/data/0059_lighting_and_illumination.hut
hidtools/data/0080_monitor.hut
hidtools/data/0081_monitor_enumerated_values.hut
hidtools/data/0082_vesa_virtual_controls.hut
hidtools/data/0083_vesa_command.hut
hidtools/data/0084_power_device.hut
hidtools/data/0085_battery_system.hut
hidtools/data/008c_bar_code_scanner.hut
hidtools/data/008d_scale.hut
hidtools/data/008e_magnetic_stripe_reading.hut
hidtools/data/0090_camera_control.hut
hidtools/data/0091_arcade_page_oaaf.hut
hidtools/data/0092_gaming_device.hut
hidtools/data/f1d0_fast_identity_online_alliance.hut
hidtools/data/ff00_vendor_defined_page_1.hut
hidtools/data/ff0d_wacom.hut
hidtools/device/base_device.py
hidtools/device/base_gamepad.py
hidtools/device/sony_gamepad.py
hid_tools-0.10.data/data/share/man/man1/hid-decode.1
hid_tools-0.10.data/data/share/man/man1/hid-recorder.1
hid_tools-0.10.data/data/share/man/man1/hid-replay.1
hid_tools-0.10.dist-info/METADATA
hid_tools-0.10.dist-info/WHEEL
hid_tools-0.10.dist-info/entry_points.txt
hid_tools-0.10.dist-info/licenses/COPYING
hid_tools-0.10.dist-info/RECORD
