Metadata-Version: 2.4
Name: hid-tools
Version: 0.10
Summary: HID tools
Project-URL: Homepage, http://gitlab.freedesktop.org/libevdev/hid-tools
Author-email: Benjamin Tissoires <benjamin.tissoires@redhat.com>
License-Expression: GPL-2.0-only
License-File: COPYING
Classifier: Development Status :: 3 - Alpha
Classifier: License :: OSI Approved :: GNU General Public License v2 or later (GPLv2+)
Classifier: Programming Language :: Python :: 3
Classifier: Programming Language :: Python :: 3.9
Requires-Python: >=3.9
Requires-Dist: click
Requires-Dist: libevdev
Requires-Dist: parse
Requires-Dist: pyroute2
Requires-Dist: pyyaml
Requires-Dist: typing-extensions
Provides-Extra: uhid
Requires-Dist: pyudev; extra == 'uhid'
